Lab-Report-2/code-files/q1/design.v
module SRFlipFlop(S,R,clock,Q,Qbar);
input S,R,clock;
output reg Q=0,Qbar=1;

always@(posedge clock)
begin
  if(S & ~R)
    begin
      Q <= 1;
      Qbar <= 0;
    end
  else if(~S & R)
    begin
      Q <= 0;
      Qbar <= 1;
    end
  else if(~S & ~R) 
    begin 
      Q <= Q;
      Qbar <= Qbar;
    end
  else if(S & R)
    begin
      Q <= 1'bx;
      Qbar <= 1'bx;
    end
end
endmodule

Lab-Report-2/code-files/q1/main.v
`timescale 1s/100ms
`include "design.v"

module main();

reg clk;
wire q0,q0bar,q1,q1bar,q2,q2bar,q3,q3bar;

//Instantation of flip flops
SRFlipFlop ff0(q1bar ^ q2bar ^ q3bar,q1 ^ q2 ^ q3,clk,q0,q0bar);
SRFlipFlop ff1(q0 & (q3bar ^ q2),q0 & (q3 ^ q2),clk,q1,q1bar);
SRFlipFlop ff2(q3bar & q1 & q0bar,q3 & q1 & q0bar,clk,q2,q2bar);
SRFlipFlop ff3(q2 & q1bar & q0bar,q2bar & q1bar & q0bar,clk,q3,q3bar);

initial 
begin
$monitor("CLK=%b,q3=%b,q2=%b,q1=%b,q0=%b",clk,q3,q2,q1,q0);
$dumpfile("design.vcd");
$dumpvars(0,main);
  clk=0; //intitially clock=0;
  #160; //simulation time (enough for all states to occur)
  $finish;
end
always 
  #5 clk = ~clk; //changing clock after every 5s
endmodule

Lab-Report-2/code-files/q1/design.vcd
$date
	Mon Mar 14 21:19:40 2022
$end
$version
	Icarus Verilog
$end
$timescale
	100ms
$end
$scope module main $end
$var wire 1 ! q3bar $end
$var wire 1 " q3 $end
$var wire 1 # q2bar $end
$var wire 1 $ q2 $end
$var wire 1 % q1bar $end
$var wire 1 & q1 $end
$var wire 1 ' q0bar $end
$var wire 1 ( q0 $end
$var reg 1 ) clk $end
$scope module ff0 $end
$var wire 1 * R $end
$var wire 1 + S $end
$var wire 1 ) clock $end
$var reg 1 ( Q $end
$var reg 1 ' Qbar $end
$upscope $end
$scope module ff1 $end
$var wire 1 , R $end
$var wire 1 - S $end
$var wire 1 ) clock $end
$var reg 1 & Q $end
$var reg 1 % Qbar $end
$upscope $end
$scope module ff2 $end
$var wire 1 . R $end
$var wire 1 / S $end
$var wire 1 ) clock $end
$var reg 1 $ Q $end
$var reg 1 # Qbar $end
$upscope $end
$scope module ff3 $end
$var wire 1 0 R $end
$var wire 1 1 S $end
$var wire 1 ) clock $end
$var reg 1 " Q $end
$var reg 1 ! Qbar $end
$upscope $end
$upscope $end
$enddefinitions $end
#0
$dumpvars
01
10
0/
0.
0-
0,
1+
0*
0)
0(
1'
0&
1%
0$
1#
0"
1!
$end
#50
00
1-
0'
1(
1)
#100
0)
#150
0+
1*
0%
1&
1)
#200
0)
#250
1/
0-
1'
0(
1)
#300
0)
#350
1+
0*
0#
1$
1)
#400
0)
#450
0/
1,
0'
1(
1)
#500
0)
#550
0+
1*
1%
0&
1)
#600
0)
#650
11
0,
1'
0(
1)
#700
0)
#750
1+
0*
0!
1"
1)
#800
0)
#850
01
1-
0'
1(
1)
#900
0)
#950
0+
1*
0%
1&
1)
#1000
0)
#1050
1.
0-
1'
0(
1)
#1100
0)
#1150
1+
0*
1#
0$
1)
#1200
0)
#1250
0.
1,
0'
1(
1)
#1300
0)
#1350
0+
1*
1%
0&
1)
#1400
0)
#1450
10
0,
1'
0(
1)
#1500
0)
#1550
1+
0*
1!
0"
1)
