Lab-Report-1/Files/code_files/design.v
module kmap(A,B,C,D,out);
  input A,B,C,D;
  output out;
  assign out = (A & D) | (~B & ~C) | (~C & D) | (~A & C & ~D) | (B & C & ~D);
endmodule

module mux8x1(i0,i1,i2,i3,i4,i5,i6,i7,sel0,sel1,sel2,out);
input i0,i1,i2,i3,i4,i5,i6,i7,sel0,sel1,sel2;
output reg out;
always@(*)
  begin
    if (~sel2 & ~sel1 & ~sel0)
      out=i0;
    else if (~sel2 & ~sel1 & sel0)
      out=i1;
    else if (~sel2 & sel1 & ~sel0)
      out=i2;
    else if (~sel2 & sel1 & sel0)
      out=i3;
    else if (sel2 & ~sel1 & ~sel0)
      out=i4;
    else if (sel2 & ~sel1 & sel0)
      out=i5;
    else if (sel2 & sel1 & ~sel0)
      out=i6;
    else if (sel2 & sel1 & sel0)
      out=i7;
  end
endmodule

module mux4x1(i0,i1,i2,i3,sel0,sel1,E,out); //E is enable line
input i0,i1,i2,i3,sel0,sel1,E;
output reg out;
always@(*)
  begin
    if(E)
      out=0; //if the mux is not active then giving 0 output
    else if (~sel1 & ~sel0)
      out=i0;
    else if (~sel1 & sel0)
      out=i1;
    else if (sel1 & ~sel0)
      out=i2;
    else if (sel1 & sel0)
      out=i3;
  end
endmodule

module ORgate(in1,in2,out);
input in1,in2;
output out;
assign out=in1|in2;
endmodule

Lab-Report-1/Files/code_files/main.v
`timescale 1s/100ms
`include "design.v" //inlcuding the gates implementation file

module main(); //module of the testbench starts
reg a,b,c,d;
wire F; wire y1,y2; wire out1,out2;

//instantitation the design module and passing the parameters
// case a:
mux8x1 func1(1,1,~a,a,0,1,1,a,d,c,b,y1);// 8x1 MUX

// case b:
mux4x1 func2(1,1,~a,a,d,c,b,out1); //4x1 MUX-1
mux4x1 func3(0,1,1,a,d,c,~b,out2);// 4x1 MUX-2
ORgate func4(out1,out2,y2);

//Realising function using k-maps
kmap func5(a,b,c,d,F);

initial 
begin
  $monitor("a=%b,b=%b,c=%b,d=%b,y1=%b,y2=%b,F=%b",a,b,c,d,y1,y2,F);
  $dumpfile("design.vcd"); 
  $dumpvars(0,main);

  a=0;b=0;c=0;d=0;#10; 
  a=0;b=0;c=0;d=1;#10;
  a=0;b=0;c=1;d=0;#10;
  a=0;b=0;c=1;d=1;#10;
  
  a=0;b=1;c=0;d=0;#10;
  a=0;b=1;c=0;d=1;#10;
  a=0;b=1;c=1;d=0;#10;
  a=0;b=1;c=1;d=1;#10;

  a=1;b=0;c=0;d=0;#10;
  a=1;b=0;c=0;d=1;#10;
  a=1;b=0;c=1;d=0;#10;
  a=1;b=0;c=1;d=1;#10;

  a=1;b=1;c=0;d=0;#10;
  a=1;b=1;c=0;d=1;#10;
  a=1;b=1;c=1;d=0;#10;
  a=1;b=1;c=1;d=1;#10;

  $finish;
end
endmodule

Lab-Report-1/Files/code_files/design.vcd
$date
	Tue Feb 22 17:02:56 2022
$end
$version
	Icarus Verilog
$end
$timescale
	100ms
$end
$scope module main $end
$var wire 1 ! y2 $end
$var wire 1 " y1 $end
$var wire 1 # out2 $end
$var wire 1 $ out1 $end
$var wire 1 % F $end
$var reg 1 & a $end
$var reg 1 ' b $end
$var reg 1 ( c $end
$var reg 1 ) d $end
$scope module func1 $end
$var wire 1 * i0 $end
$var wire 1 + i1 $end
$var wire 1 , i2 $end
$var wire 1 & i3 $end
$var wire 1 - i4 $end
$var wire 1 . i5 $end
$var wire 1 / i6 $end
$var wire 1 & i7 $end
$var wire 1 ) sel0 $end
$var wire 1 ( sel1 $end
$var wire 1 ' sel2 $end
$var reg 1 " out $end
$upscope $end
$scope module func2 $end
$var wire 1 ' E $end
$var wire 1 0 i0 $end
$var wire 1 1 i1 $end
$var wire 1 2 i2 $end
$var wire 1 & i3 $end
$var wire 1 ) sel0 $end
$var wire 1 ( sel1 $end
$var reg 1 $ out $end
$upscope $end
$scope module func3 $end
$var wire 1 3 E $end
$var wire 1 4 i0 $end
$var wire 1 5 i1 $end
$var wire 1 6 i2 $end
$var wire 1 & i3 $end
$var wire 1 ) sel0 $end
$var wire 1 ( sel1 $end
$var reg 1 # out $end
$upscope $end
$scope module func4 $end
$var wire 1 $ in1 $end
$var wire 1 # in2 $end
$var wire 1 ! out $end
$upscope $end
$scope module func5 $end
$var wire 1 & A $end
$var wire 1 ' B $end
$var wire 1 ( C $end
$var wire 1 ) D $end
$var wire 1 % out $end
$upscope $end
$upscope $end
$enddefinitions $end
#0
$dumpvars
16
15
04
13
12
11
10
1/
1.
0-
1,
1+
1*
0)
0(
0'
0&
1%
1$
0#
1"
1!
$end
#100
1)
#200
0)
1(
#300
0%
0!
0"
0$
1)
#400
03
0)
0(
1'
#500
1%
1!
1"
1#
1)
#600
0)
1(
#700
0%
0!
0"
0#
1)
#800
1%
1!
13
1"
1$
02
0,
0)
0(
0'
1&
#900
1)
#1000
0%
0!
0"
0$
0)
1(
#1100
1%
1!
1"
1$
1)
#1200
0%
0!
0"
0$
03
0)
0(
1'
#1300
1%
1!
1"
1#
1)
#1400
0)
1(
#1500
1%
1)
