Lab-Report-3/code-files/design.v
module DFlipFlop(D,clock,preset,Q,Qbar);
input D,clock,preset;
output reg Q,Qbar;

initial
begin
  if(~preset)
  begin
    Q=1;Qbar=0;
  end
  else
  begin
    Q=0;Qbar=1;
  end
end

always@(posedge clock)
begin
  Q <= D;
  Qbar <= ~D;
end
endmodule

module FSM(in,out,clock,q2,q1,q0,q2bar,q1bar,q0bar);
input in,clock;
output wire q2,q1,q0,q2bar,q1bar,q0bar;
output reg out=0;

DFlipFlop ff1((q0bar & in)|(q1 & q0bar)|(q2 & q0bar),clock,1'b1,q0,q0bar);
DFlipFlop ff2((q2bar & q1bar & q0)|(q1 & q0bar),clock,1'b1,q1,q1bar);
DFlipFlop ff3((q2 & q0bar)|(q1 &q0),clock,1'b1,q2,q2bar);
always @(posedge clock ) 
begin
  assign out=(q1 & q0bar)|(q2bar & q0bar & in);
end
endmodule

Lab-Report-3/code-files/main.v
`timescale 1s/100ms
`include "design.v"

module main();

reg clk,in;
wire q0,q1,q2,q2bar,q1bar,q0bar,out;

//Instantating the finite state machine
FSM func(in,out,clk,q2,q1,q0,q2bar,q1bar,q0bar);

initial 
begin
$monitor("CLK=%b,out=%b,in=%b,q2=%b,q1=%b,q0=%b",clk,out,in,q2,q1,q0);
$dumpfile("design.vcd");
$dumpvars(0,main);
  clk=0; //initially clock=0;
  in=1;#60 //initially input=1;
  in=0;#60; //after running the simulation for 60s, input is made 0;
  in=1;#10;in=0;
  #60;
  $finish;
end
always 
  #5 clk = ~clk; //changing clock after every 5s
endmodule

Lab-Report-3/code-files/design.vcd
$date
	Tue Mar 29 21:06:46 2022
$end
$version
	Icarus Verilog
$end
$timescale
	100ms
$end
$scope module main $end
$var wire 1 ! q2bar $end
$var wire 1 " q2 $end
$var wire 1 # q1bar $end
$var wire 1 $ q1 $end
$var wire 1 % q0bar $end
$var wire 1 & q0 $end
$var wire 1 ' out $end
$var reg 1 ( clk $end
$var reg 1 ) in $end
$scope module func $end
$var wire 1 ( clock $end
$var wire 1 ) in $end
$var wire 1 ! q2bar $end
$var wire 1 " q2 $end
$var wire 1 # q1bar $end
$var wire 1 $ q1 $end
$var wire 1 % q0bar $end
$var wire 1 & q0 $end
$var reg 1 ' out $end
$scope module ff1 $end
$var wire 1 * D $end
$var wire 1 ( clock $end
$var wire 1 + preset $end
$var reg 1 & Q $end
$var reg 1 % Qbar $end
$upscope $end
$scope module ff2 $end
$var wire 1 , D $end
$var wire 1 ( clock $end
$var wire 1 - preset $end
$var reg 1 $ Q $end
$var reg 1 # Qbar $end
$upscope $end
$scope module ff3 $end
$var wire 1 . D $end
$var wire 1 ( clock $end
$var wire 1 / preset $end
$var reg 1 " Q $end
$var reg 1 ! Qbar $end
$upscope $end
$upscope $end
$upscope $end
$enddefinitions $end
#0
$dumpvars
1/
0.
1-
0,
1+
1*
1)
0(
0'
0&
1%
0$
1#
0"
1!
$end
#50
0*
1,
0%
1&
1'
1(
#100
0(
#150
1*
0#
1$
1%
0&
0'
1(
#200
0(
#250
0*
0,
1.
0%
1&
1'
1(
#300
0(
#350
1*
0!
1"
1#
0$
1%
0&
0'
1(
#400
0(
#450
0.
0*
0%
1&
1(
#500
0(
#550
1*
1!
0"
1%
0&
1(
#600
0*
0(
0)
#650
1(
#700
0(
#750
1(
#800
0(
#850
1(
#900
0(
#950
1(
#1000
0(
#1050
1(
#1100
0(
#1150
1(
#1200
1*
0(
1)
#1250
0*
1,
0%
1&
1'
1(
#1300
0(
0)
#1350
1*
0#
1$
1%
0&
0'
1(
#1400
0(
#1450
0*
0,
1.
0%
1&
1'
1(
#1500
0(
#1550
1*
0!
1"
1#
0$
1%
0&
0'
1(
#1600
0(
#1650
0.
0*
0%
1&
1(
#1700
0(
#1750
1!
0"
1%
0&
1(
